{"cameraMode":{"drawMode":0,"name":"Shaded","section":"Shading Mode"},"sceneLighting":true,"audioPlay":false,"sceneViewState":{"m_AlwaysRefresh":false,"showFog":true,"showSkybox":true,"showFlares":true,"showImageEffects":true,"showParticleSystems":true,"showVisualEffectGraphs":true,"m_FxEnabled":true},"in2DMode":false,"pivot":{"x":-0.680883526802063,"y":-40.76832580566406,"z":-0.05415257811546326},"rotation":{"x":-0.28387314081192019,"y":0.6518083810806274,"z":-0.6413485407829285,"w":-0.2885030210018158},"size":88.10029602050781,"orthographic":false}